README.md
pyproject.toml
setup.cfg
setup.py
iparapheur_provisioning/__init__.py
iparapheur_provisioning/api_client.py
iparapheur_provisioning/api_response.py
iparapheur_provisioning/configuration.py
iparapheur_provisioning/exceptions.py
iparapheur_provisioning/py.typed
iparapheur_provisioning/rest.py
iparapheur_provisioning.egg-info/PKG-INFO
iparapheur_provisioning.egg-info/SOURCES.txt
iparapheur_provisioning.egg-info/dependency_links.txt
iparapheur_provisioning.egg-info/requires.txt
iparapheur_provisioning.egg-info/top_level.txt
iparapheur_provisioning/api/__init__.py
iparapheur_provisioning/api/admin_all_users_api.py
iparapheur_provisioning/api/admin_desk_api.py
iparapheur_provisioning/api/admin_external_signature_api.py
iparapheur_provisioning/api/admin_folder_api.py
iparapheur_provisioning/api/admin_metadata_api.py
iparapheur_provisioning/api/admin_seal_certificate_api.py
iparapheur_provisioning/api/admin_secure_mail_api.py
iparapheur_provisioning/api/admin_template_api.py
iparapheur_provisioning/api/admin_tenant_api.py
iparapheur_provisioning/api/admin_tenant_user_api.py
iparapheur_provisioning/api/admin_typology_api.py
iparapheur_provisioning/api/admin_workflow_definition_api.py
iparapheur_provisioning/models/__init__.py
iparapheur_provisioning/models/certificate_informations.py
iparapheur_provisioning/models/create_seal_certificate_deprecated_request.py
iparapheur_provisioning/models/delegation_dto.py
iparapheur_provisioning/models/delegation_sort_by.py
iparapheur_provisioning/models/desk_dto.py
iparapheur_provisioning/models/desk_representation.py
iparapheur_provisioning/models/error_response.py
iparapheur_provisioning/models/external_signature_config_dto.py
iparapheur_provisioning/models/external_signature_config_representation.py
iparapheur_provisioning/models/external_signature_config_sort_by.py
iparapheur_provisioning/models/external_signature_level.py
iparapheur_provisioning/models/external_signature_provider.py
iparapheur_provisioning/models/internal_metadata.py
iparapheur_provisioning/models/layer_representation.py
iparapheur_provisioning/models/layer_sort_by.py
iparapheur_provisioning/models/listable_user.py
iparapheur_provisioning/models/metadata_dto.py
